dennis_systems/__init__.py
dennis_systems/core/__init__.py
dennis_systems/core/shared-lib/Authorization.py
dennis_systems/core/shared-lib/AuthorizationResponse.py
dennis_systems/core/shared-lib/__init__.py
dennis_systems/core/shared-lib/utils.py
dennis_systems/core/shared_lib/Authorization.py
dennis_systems/core/shared_lib/AuthorizationResponse.py
dennis_systems/core/shared_lib/__init__.py
dennis_systems/core/shared_lib/utils.py
dennis_systems/core/shared_lib/api/ApiDefault.py
dennis_systems/core/shared_lib/api/PermissionAll.py
dennis_systems/core/shared_lib/api/__init__.py
dennis_systems/core/shared_lib/auth/Authorization.py
dennis_systems/core/shared_lib/auth/AuthorizationResponse.py
dennis_systems/core/shared_lib/auth/__init__.py
dennis_systems/core/shared_lib/entity/BaseModel.py
dennis_systems/core/shared_lib/entity/__init__.py
dennis_systems/core/shared_lib/service/DefaultService.py
dennis_systems/core/shared_lib/service/__init__.py
dennis_systems/core/shared_lib/utils/__init__.py
dennis_systems/core/shared_lib/utils/utils.py
ru/__init__.py
ru/mp/__init__.py
ru/mp/shared-lib/Authorization.py
ru/mp/shared-lib/AuthorizationResponse.py
ru/mp/shared-lib/__init__.py
ru/mp/shared-lib/utils.py
dennis_systems_core-0.0.10.dist-info/METADATA
dennis_systems_core-0.0.10.dist-info/WHEEL
dennis_systems_core-0.0.10.dist-info/top_level.txt
dennis_systems_core-0.0.10.dist-info/RECORD
