Metadata-Version: 2.1
Name: dennis-systems-core
Version: 0.0.10
Summary: Authorization model
Home-page: https://github.com/pypa/sampleproject
Author: Denis Oleshko
Author-email: dennis.oleshko@gmail.com
Classifier: Programming Language :: Python :: 3
Classifier: License :: OSI Approved :: MIT License
Classifier: Operating System :: OS Independent
